odoo/addons/pos_operating_unit/README.rst
odoo/addons/pos_operating_unit/__init__.py
odoo/addons/pos_operating_unit/__manifest__.py
odoo/addons/pos_operating_unit/i18n/es.po
odoo/addons/pos_operating_unit/i18n/it.po
odoo/addons/pos_operating_unit/i18n/pos_operating_unit.pot
odoo/addons/pos_operating_unit/models/__init__.py
odoo/addons/pos_operating_unit/models/pos_config.py
odoo/addons/pos_operating_unit/models/pos_order.py
odoo/addons/pos_operating_unit/models/pos_payment.py
odoo/addons/pos_operating_unit/models/pos_session.py
odoo/addons/pos_operating_unit/models/res_config_settings.py
odoo/addons/pos_operating_unit/readme/CONTRIBUTORS.md
odoo/addons/pos_operating_unit/readme/DESCRIPTION.md
odoo/addons/pos_operating_unit/readme/ROADMAP.md
odoo/addons/pos_operating_unit/readme/USAGE.md
odoo/addons/pos_operating_unit/security/pos_security.xml
odoo/addons/pos_operating_unit/static/description/icon.png
odoo/addons/pos_operating_unit/static/description/index.html
odoo/addons/pos_operating_unit/tests/__init__.py
odoo/addons/pos_operating_unit/tests/test_pos_operating_unit.py
odoo/addons/pos_operating_unit/views/pos_views.xml
odoo/addons/pos_operating_unit/views/res_config_settings_views.xml
odoo_addon_pos_operating_unit-17.0.1.0.0.4.dist-info/METADATA
odoo_addon_pos_operating_unit-17.0.1.0.0.4.dist-info/WHEEL
odoo_addon_pos_operating_unit-17.0.1.0.0.4.dist-info/top_level.txt
odoo_addon_pos_operating_unit-17.0.1.0.0.4.dist-info/RECORD
